onelive_restream/__init__.py
onelive_restream/api_client.py
onelive_restream/shared/__init__.py
onelive_restream/shared/enums/__init__.py
onelive_restream/shared/enums/proxy_type.py
onelive_restream/shared/enums/stream_state.py
onelive_restream/shared/errors/__init__.py
onelive_restream/shared/errors/auth.py
onelive_restream/shared/errors/profile.py
onelive_restream/shared/errors/proxy.py
onelive_restream/shared/errors/server.py
onelive_restream/shared/errors/site.py
onelive_restream/shared/errors/stream.py
onelive_restream/shared/models/__init__.py
onelive_restream/shared/models/auth.py
onelive_restream/shared/models/banner.py
onelive_restream/shared/models/base.py
onelive_restream/shared/models/profile.py
onelive_restream/shared/models/proxy.py
onelive_restream/shared/models/request_auth.py
onelive_restream/shared/models/rtmp.py
onelive_restream/shared/models/selector.py
onelive_restream/shared/models/server.py
onelive_restream/shared/models/site.py
onelive_restream/shared/models/stream.py
onelive_restream/shared/models/stream_banner.py
onelive_restream/shared/models/vnc.py
onelive_restream/shared/requests_data/__init__.py
onelive_restream/shared/requests_data/banner.py
onelive_restream/shared/requests_data/profile.py
onelive_restream/shared/requests_data/proxy.py
onelive_restream/shared/requests_data/rtmp.py
onelive_restream/shared/requests_data/selector.py
onelive_restream/shared/requests_data/server.py
onelive_restream/shared/requests_data/site.py
onelive_restream/shared/requests_data/stream.py
onelive_restream/shared/requests_data/stream_banner.py
onelive_restream/shared/requests_data/stream_server.py
onelive_restream/shared/requests_data/vnc.py
onelive_restream/shared/responses_data/__init__.py
onelive_restream/shared/responses_data/banner.py
onelive_restream/shared/responses_data/profile.py
onelive_restream/shared/responses_data/proxy.py
onelive_restream/shared/responses_data/rtmp.py
onelive_restream/shared/responses_data/selector.py
onelive_restream-0.2.10.dist-info/LICENSE
onelive_restream-0.2.10.dist-info/METADATA
onelive_restream-0.2.10.dist-info/WHEEL
onelive_restream-0.2.10.dist-info/top_level.txt
onelive_restream-0.2.10.dist-info/RECORD
