Metadata-Version: 2.1
Name: onelive_restream
Version: 0.2.10
Summary: Restreaming for the customer
Home-page: https://nexium.me
Author: Nexium
Author-email: info@nexium.me
License: MIT
Classifier: Programming Language :: Python :: 3
Classifier: License :: OSI Approved :: MIT License
Classifier: Operating System :: OS Independent
Requires-Python: >=3.11
License-File: LICENSE
Requires-Dist: nexium-api
Requires-Dist: nexium-database
